{
  "openapi": "3.0.4",
  "info": {
    "title": "ContractService.API",
    "version": "1.0"
  },
  "paths": {
    "/api/contracts": {
      "post": {
        "tags": [
          "Contract"
        ],
        "requestBody": {
          "content": {
            "application/json": {
              "schema": {
                "$ref": "#/components/schemas/CreateContractRequestDTO"
              }
            },
            "text/json": {
              "schema": {
                "$ref": "#/components/schemas/CreateContractRequestDTO"
              }
            },
            "application/*+json": {
              "schema": {
                "$ref": "#/components/schemas/CreateContractRequestDTO"
              }
            }
          }
        },
        "responses": {
          "200": {
            "description": "OK"
          }
        }
      }
    }
  },
  "components": {
    "schemas": {
      "CreateContractRequestDTO": {
        "type": "object",
        "properties": {
          "proposalId": {
            "type": "string",
            "format": "uuid"
          }
        },
        "additionalProperties": false
      }
    }
  }
}